{
  "background": {
    "bbox": {
      "h": 7.5,
      "w": 13.333,
      "x": 0,
      "y": 0
    },
    "id": "object_000",
    "properties": {
      "archetype": "atomic_composition",
      "back_color": [
        232,
        163,
        45
      ],
      "fill": [
        232,
        163,
        45
      ],
      "fore_color": [
        222,
        133,
        62
      ],
      "pattern": 26,
      "style": "pattern",
      "theme_topic": "Unknown Dramatic"
    },
    "type": "background",
    "z_order": 0
  },
  "curriculum": {
    "actual_content_count": 21,
    "level": 21,
    "max_level": 25,
    "slides_per_level": 40,
    "target_content_count": 21
  },
  "objects": [
    {
      "bbox": {
        "h": 3.0665,
        "w": 8.5919,
        "x": 2.4517,
        "y": 1.3815
      },
      "id": "object_001",
      "properties": {
        "archetype": "atomic_composition",
        "dash": 2,
        "family": "stars",
        "fill": [
          125,
          139,
          109
        ],
        "focus": false,
        "line": [
          195,
          129,
          200
        ],
        "line_width": 4.409158867720542,
        "outline_only": false,
        "ppt_type": 90,
        "shape": "explosion2",
        "theme_topic": "Unknown Dramatic"
      },
      "type": "shape",
      "z_order": 1
    },
    {
      "bbox": {
        "h": 3.6384,
        "w": 7.0015,
        "x": 2.4035,
        "y": 4.6219
      },
      "id": "object_002",
      "properties": {
        "archetype": "atomic_composition",
        "dash": 1,
        "family": "callouts",
        "fill": [
          95,
          183,
          86
        ],
        "focus": false,
        "line": [
          39,
          190,
          32
        ],
        "line_width": 7.202582496725544,
        "outline_only": false,
        "ppt_type": 107,
        "shape": "oval_callout",
        "theme_topic": "Unknown Dramatic"
      },
      "type": "shape",
      "z_order": 2
    },
    {
      "bbox": {
        "h": 1.4837,
        "w": 7.8301,
        "x": 5.7026,
        "y": 4.9995
      },
      "id": "object_003",
      "properties": {
        "archetype": "atomic_composition",
        "dash": 1,
        "family": "stars",
        "fill": [
          108,
          76,
          29
        ],
        "focus": false,
        "line": [
          211,
          213,
          200
        ],
        "line_width": 4.974092385801866,
        "outline_only": true,
        "ppt_type": 91,
        "shape": "star4",
        "theme_topic": "Unknown Dramatic"
      },
      "type": "shape",
      "z_order": 3
    },
    {
      "bbox": {
        "h": 3.5769,
        "w": 6.9765,
        "x": 1.1992,
        "y": 1.689
      },
      "id": "object_004",
      "properties": {
        "archetype": "atomic_composition",
        "dash": 1,
        "family": "panel",
        "fill": [
          206,
          144,
          39
        ],
        "line": [
          193,
          135,
          37
        ],
        "line_width": 5.090282776709786,
        "outline_only": false,
        "ppt_type": 5,
        "shape": "round_rect",
        "theme_topic": "Unknown Dramatic"
      },
      "type": "shape",
      "z_order": 4
    },
    {
      "bbox": {
        "h": 0.908,
        "w": 5.7441,
        "x": 3.7541,
        "y": 0.6671
      },
      "id": "object_005",
      "properties": {
        "archetype": "atomic_composition",
        "bg_color": null,
        "bold": true,
        "color": [
          28,
          30,
          36
        ],
        "font_face": "Georgia",
        "font_size": 34,
        "italic": false,
        "kind": "header",
        "margin": 0.04,
        "text": "Dangerous Bone",
        "theme_topic": "Unknown Dramatic",
        "underline": false
      },
      "type": "text",
      "z_order": 5
    },
    {
      "bbox": {
        "h": 2.9026,
        "w": 12.1203,
        "x": 0.5705,
        "y": 4.0337
      },
      "id": "object_006",
      "properties": {
        "archetype": "atomic_composition",
        "band": [
          115,
          139,
          121
        ],
        "band_cols": false,
        "band_rows": true,
        "body": [
          193,
          135,
          37
        ],
        "border": [
          146,
          127,
          167
        ],
        "border_dash": "solid",
        "border_width": 1.521241557800792,
        "cells": [
          [
            "rebel",
            "flavor nostalgic",
            "strange whimsical",
            "wary"
          ],
          [
            "lovely plastic",
            "uppity",
            "whirl",
            "pies verse"
          ]
        ],
        "cols": 4,
        "font_size": 7,
        "has_header": true,
        "header": [
          26,
          80,
          70
        ],
        "rows": 2,
        "text_color": [
          65,
          146,
          182
        ],
        "theme_topic": "Unknown Dramatic"
      },
      "type": "table",
      "z_order": 6
    },
    {
      "bbox": {
        "h": 2.262,
        "w": 3.7932,
        "x": 0.5561,
        "y": 1.4326
      },
      "id": "object_007",
      "properties": {
        "archetype": "atomic_composition",
        "dash": 7,
        "family": "panel",
        "fill": [
          193,
          135,
          37
        ],
        "line": [
          193,
          135,
          37
        ],
        "line_width": 4.883741527015319,
        "outline_only": false,
        "ppt_type": 5,
        "shape": "round_rect",
        "theme_topic": "Unknown Dramatic"
      },
      "type": "shape",
      "z_order": 7
    },
    {
      "bbox": {
        "h": 0.431,
        "w": 3.3128,
        "x": 0.789,
        "y": 2.3383
      },
      "id": "object_008",
      "properties": {
        "archetype": "atomic_composition",
        "bg_color": null,
        "bold": true,
        "color": [
          31,
          117,
          161
        ],
        "font_face": "Aptos",
        "font_size": 10,
        "italic": false,
        "kind": "caption",
        "margin": 0.03,
        "text": "Attach",
        "theme_topic": "Unknown Dramatic",
        "underline": false
      },
      "type": "text",
      "z_order": 8
    },
    {
      "bbox": {
        "h": 0.6183,
        "w": 3.2763,
        "x": 0.7916,
        "y": 2.9216
      },
      "id": "object_009",
      "properties": {
        "archetype": "atomic_composition",
        "bg_color": null,
        "bold": false,
        "color": [
          119,
          89,
          40
        ],
        "font_face": "Aptos",
        "font_size": 14,
        "italic": false,
        "kind": "body",
        "margin": 0.04,
        "text": "swift allow design versed young ladybug avoid plastic cultured rain",
        "theme_topic": "Unknown Dramatic",
        "underline": false
      },
      "type": "text",
      "z_order": 9
    },
    {
      "bbox": {
        "h": 2.2447,
        "w": 3.6904,
        "x": 4.5797,
        "y": 1.4351
      },
      "id": "object_010",
      "properties": {
        "archetype": "atomic_composition",
        "dash": 1,
        "family": "panel",
        "fill": [
          193,
          135,
          37
        ],
        "line": [
          193,
          135,
          37
        ],
        "line_width": 3.415646211504331,
        "outline_only": false,
        "ppt_type": 5,
        "shape": "round_rect",
        "theme_topic": "Unknown Dramatic"
      },
      "type": "shape",
      "z_order": 10
    },
    {
      "bbox": {
        "h": 0.5625,
        "w": 0.5487,
        "x": 4.8193,
        "y": 1.654
      },
      "id": "object_011",
      "properties": {
        "archetype": "atomic_composition",
        "dash": 1,
        "family": "arrows",
        "fill": [
          64,
          149,
          53
        ],
        "focus": false,
        "line": [
          31,
          117,
          161
        ],
        "line_width": 2.4885553819447415,
        "outline_only": false,
        "ppt_type": 53,
        "shape": "right_arrow_callout",
        "theme_topic": "Unknown Dramatic"
      },
      "type": "shape",
      "z_order": 11
    },
    {
      "bbox": {
        "h": 0.4605,
        "w": 3.1848,
        "x": 4.8383,
        "y": 2.3425
      },
      "id": "object_012",
      "properties": {
        "archetype": "atomic_composition",
        "bg_color": null,
        "bold": true,
        "color": [
          31,
          117,
          161
        ],
        "font_face": "Aptos",
        "font_size": 9,
        "italic": false,
        "kind": "caption",
        "margin": 0.03,
        "text": "Cowardly",
        "theme_topic": "Unknown Dramatic",
        "underline": false
      },
      "type": "text",
      "z_order": 12
    },
    {
      "bbox": {
        "h": 0.614,
        "w": 3.2326,
        "x": 4.7976,
        "y": 2.9099
      },
      "id": "object_013",
      "properties": {
        "archetype": "atomic_composition",
        "bg_color": null,
        "bold": false,
        "color": [
          119,
          89,
          40
        ],
        "font_face": "Aptos",
        "font_size": 11,
        "italic": false,
        "kind": "body",
        "margin": 0.04,
        "text": "lame bushes boring pocket yell harmony ski helpless courageous dusty unused glistening flat shut precede",
        "theme_topic": "Unknown Dramatic",
        "underline": false
      },
      "type": "text",
      "z_order": 13
    },
    {
      "bbox": {
        "h": 2.251,
        "w": 4.2855,
        "x": 8.4858,
        "y": 1.4415
      },
      "id": "object_014",
      "properties": {
        "archetype": "atomic_composition",
        "dash": 4,
        "family": "panel",
        "fill": [
          193,
          135,
          37
        ],
        "line": [
          193,
          135,
          37
        ],
        "line_width": 0.6934894851334235,
        "outline_only": false,
        "ppt_type": 5,
        "shape": "round_rect",
        "theme_topic": "Unknown Dramatic"
      },
      "type": "shape",
      "z_order": 14
    },
    {
      "bbox": {
        "h": 0.5413,
        "w": 0.5669,
        "x": 8.7407,
        "y": 1.6581
      },
      "id": "object_015",
      "properties": {
        "archetype": "atomic_composition",
        "dash": 1,
        "family": "flowchart",
        "fill": [
          31,
          117,
          161
        ],
        "focus": false,
        "line": [
          119,
          89,
          40
        ],
        "line_width": 1.3578058249905876,
        "outline_only": false,
        "ppt_type": 65,
        "shape": "flow_predefined",
        "theme_topic": "Unknown Dramatic"
      },
      "type": "shape",
      "z_order": 15
    },
    {
      "bbox": {
        "h": 0.4313,
        "w": 3.7919,
        "x": 8.766,
        "y": 2.3359
      },
      "id": "object_016",
      "properties": {
        "archetype": "atomic_composition",
        "bg_color": null,
        "bold": true,
        "color": [
          31,
          117,
          161
        ],
        "font_face": "Aptos",
        "font_size": 11,
        "italic": false,
        "kind": "caption",
        "margin": 0.03,
        "text": "Face",
        "theme_topic": "Unknown Dramatic",
        "underline": false
      },
      "type": "text",
      "z_order": 16
    },
    {
      "bbox": {
        "h": 0.6004,
        "w": 3.8051,
        "x": 8.7459,
        "y": 2.9202
      },
      "id": "object_017",
      "properties": {
        "archetype": "atomic_composition",
        "bg_color": null,
        "bold": false,
        "color": [
          119,
          89,
          40
        ],
        "font_face": "Aptos",
        "font_size": 11,
        "italic": false,
        "kind": "body",
        "margin": 0.04,
        "text": "dogs disgusting wealth protest bump magnificent general include obeisant grain fetch detailed",
        "theme_topic": "Unknown Dramatic",
        "underline": false
      },
      "type": "text",
      "z_order": 17
    },
    {
      "bbox": {
        "h": 1.0934,
        "w": 1.5702,
        "x": 10.9606,
        "y": 6.1086
      },
      "id": "object_018",
      "properties": {
        "archetype": "atomic_composition",
        "pattern": "ribbon_path",
        "primary": [
          164,
          156,
          216
        ],
        "secondary": [
          222,
          133,
          62
        ],
        "svg": "<svg xmlns=\"http://www.w3.org/2000/svg\" width=\"400\" height=\"300\" viewBox=\"0 0 400 300\">\n        <path d=\"M24 84 C94 16 172 18 224 78 C278 142 334 96 376 42 L376 210 C304 260 230 244 178 190 C116 128 74 168 24 226 Z\"\n              fill=\"#22a991\" opacity=\"0.82\"/>\n        <path d=\"M54 118 C120 54 178 66 226 118 C270 166 318 142 354 104\"\n              fill=\"none\" stroke=\"#3c7565\" stroke-width=\"18\" stroke-linecap=\"round\"/>\n        </svg>",
        "theme_topic": "Unknown Dramatic"
      },
      "type": "svg",
      "z_order": 18
    },
    {
      "bbox": {
        "h": 1.0132,
        "w": 1.2535,
        "x": 1.9187,
        "y": 0.4433
      },
      "id": "object_019",
      "properties": {
        "archetype": "atomic_composition",
        "color": [
          61,
          68,
          180
        ],
        "connector": "straight",
        "dash": 3,
        "flip": false,
        "ppt_type": 1,
        "theme_topic": "Unknown Dramatic",
        "width": 2.43457130586555
      },
      "type": "connector",
      "z_order": 19
    },
    {
      "bbox": {
        "h": 0.6768,
        "w": 0.2271,
        "x": 12.2876,
        "y": 5.5525
      },
      "id": "object_020",
      "properties": {
        "archetype": "atomic_composition",
        "dash": 1,
        "family": "arrows",
        "fill": [
          197,
          211,
          151
        ],
        "focus": false,
        "line": [
          173,
          151,
          38
        ],
        "line_width": 3.306273186959842,
        "outline_only": false,
        "ppt_type": 42,
        "shape": "uturn_arrow",
        "theme_topic": "Unknown Dramatic"
      },
      "type": "shape",
      "z_order": 20
    },
    {
      "bbox": {
        "h": 0.5879,
        "w": 0.9123,
        "x": 9.125,
        "y": 5.7955
      },
      "id": "object_021",
      "properties": {
        "archetype": "atomic_composition",
        "bg_color": null,
        "bold": true,
        "color": [
          127,
          111,
          32
        ],
        "font_face": "Aptos",
        "font_size": 8,
        "italic": false,
        "kind": "body",
        "margin": 0.04,
        "text": "curve grandmother shelter recognise",
        "theme_topic": "Unknown Dramatic",
        "underline": true
      },
      "type": "text",
      "z_order": 21
    }
  ],
  "slide": {
    "height": 7.5,
    "image_file": "slide_000835.jpg",
    "width": 13.333
  },
  "version": 1
}