{
  "background": {
    "bbox": {
      "h": 7.5,
      "w": 13.333,
      "x": 0,
      "y": 0
    },
    "id": "object_000",
    "properties": {
      "archetype": "atomic_composition",
      "back_color": [
        66,
        128,
        137
      ],
      "fill": [
        66,
        128,
        137
      ],
      "fore_color": [
        212,
        222,
        161
      ],
      "pattern": 11,
      "style": "pattern",
      "theme_topic": "Silent"
    },
    "type": "background",
    "z_order": 0
  },
  "objects": [
    {
      "bbox": {
        "h": 2.5232,
        "w": 6.8962,
        "x": 1.2507,
        "y": 2.505
      },
      "id": "object_001",
      "properties": {
        "archetype": "atomic_composition",
        "dash": 1,
        "family": "arrows",
        "fill": [
          40,
          180,
          76
        ],
        "focus": false,
        "line": [
          47,
          49,
          40
        ],
        "line_width": 3.9521007108484083,
        "outline_only": false,
        "ppt_type": 53,
        "shape": "right_arrow_callout",
        "theme_topic": "Silent"
      },
      "type": "shape",
      "z_order": 1
    },
    {
      "bbox": {
        "h": 7.5156,
        "w": 0.9156,
        "x": 12.4187,
        "y": -0.0183
      },
      "id": "object_002",
      "properties": {
        "archetype": "atomic_composition",
        "dash": 7,
        "family": "panel",
        "fill": [
          123,
          166,
          172
        ],
        "line": [
          123,
          166,
          172
        ],
        "line_width": 1.0156784908653833,
        "outline_only": false,
        "ppt_type": 1,
        "shape": "rect",
        "theme_topic": "Silent"
      },
      "type": "shape",
      "z_order": 2
    },
    {
      "bbox": {
        "h": 1.1462,
        "w": 7.2266,
        "x": 2.9867,
        "y": 0.6345
      },
      "id": "object_003",
      "properties": {
        "archetype": "atomic_composition",
        "bg_color": null,
        "bold": true,
        "color": [
          246,
          248,
          252
        ],
        "font_face": "Georgia",
        "font_size": 39,
        "italic": false,
        "kind": "header",
        "margin": 0.04,
        "text": "Snobbish String",
        "theme_topic": "Silent",
        "underline": false
      },
      "type": "text",
      "z_order": 3
    },
    {
      "bbox": {
        "h": 0.6921,
        "w": 5.4389,
        "x": 0.7044,
        "y": 2.1234
      },
      "id": "object_004",
      "properties": {
        "archetype": "atomic_composition",
        "bg_color": null,
        "bold": true,
        "color": [
          87,
          81,
          197
        ],
        "font_face": "Georgia",
        "font_size": 32,
        "italic": false,
        "kind": "header",
        "margin": 0.04,
        "text": "Telephone Power Hole",
        "theme_topic": "Silent",
        "underline": false
      },
      "type": "text",
      "z_order": 4
    },
    {
      "bbox": {
        "h": 0.9118,
        "w": 5.4202,
        "x": 0.6837,
        "y": 3.0518
      },
      "id": "object_005",
      "properties": {
        "archetype": "atomic_composition",
        "bg_color": null,
        "bold": false,
        "color": [
          165,
          194,
          200
        ],
        "font_face": "Aptos",
        "font_size": 12,
        "italic": false,
        "kind": "body",
        "margin": 0.04,
        "text": "contain cable thankful hook plan play amount different ear juvenile melted magic rat wing",
        "theme_topic": "Silent",
        "underline": false
      },
      "type": "text",
      "z_order": 5
    },
    {
      "bbox": {
        "h": 2.0802,
        "w": 6.1556,
        "x": 6.6792,
        "y": 2.0109
      },
      "id": "object_006",
      "properties": {
        "archetype": "atomic_composition",
        "crop": [
          0.2210186629031312,
          0.13274582886895872,
          0.005396815243710062,
          0.24649529493849626
        ],
        "focus": true,
        "mask_line": [
          50,
          158,
          28
        ],
        "mask_overlay": false,
        "theme_topic": "Silent",
        "url": "https://picsum.photos/seed/aiimgslides/900/600"
      },
      "type": "image",
      "z_order": 6
    },
    {
      "bbox": {
        "h": 2.4814,
        "w": 12.1287,
        "x": 0.588,
        "y": 4.4942
      },
      "id": "object_007",
      "properties": {
        "archetype": "atomic_composition",
        "band": [
          58,
          41,
          181
        ],
        "band_cols": false,
        "band_rows": false,
        "body": [
          123,
          166,
          172
        ],
        "border": [
          168,
          144,
          163
        ],
        "border_dash": "solid",
        "border_width": 3.420411777965969,
        "cells": [
          [
            "analyze",
            "soap eggs",
            "blade dark",
            "refuse driving",
            "park thread",
            "cool"
          ],
          [
            "button top",
            "unequal ahead",
            "tiny kitty",
            "tenuous search",
            "blue-eyed",
            "motionless cent"
          ]
        ],
        "cols": 6,
        "font_size": 8,
        "has_header": true,
        "header": [
          38,
          132,
          88
        ],
        "rows": 2,
        "text_color": [
          246,
          248,
          252
        ],
        "theme_topic": "Silent"
      },
      "type": "table",
      "z_order": 7
    },
    {
      "bbox": {
        "h": 1.2328,
        "w": 1.6177,
        "x": 5.9193,
        "y": 4.8855
      },
      "id": "object_008",
      "properties": {
        "archetype": "atomic_composition",
        "color": [
          197,
          36,
          42
        ],
        "connector": "elbow",
        "dash": 1,
        "flip": false,
        "ppt_type": 2,
        "theme_topic": "Silent",
        "width": 1.3877466220468093
      },
      "type": "connector",
      "z_order": 8
    },
    {
      "bbox": {
        "h": 0.5615,
        "w": 0.879,
        "x": 5.9794,
        "y": 4.4143
      },
      "id": "object_009",
      "properties": {
        "archetype": "atomic_composition",
        "bg_color": [
          150,
          226,
          219
        ],
        "bold": false,
        "color": [
          165,
          107,
          209
        ],
        "font_face": "Aptos",
        "font_size": 15,
        "italic": true,
        "kind": "caption",
        "margin": 0.03,
        "text": "Old Shaggy",
        "theme_topic": "Silent",
        "underline": true
      },
      "type": "text",
      "z_order": 9
    },
    {
      "bbox": {
        "h": 0.5429,
        "w": 1.6068,
        "x": 1.6956,
        "y": 3.2677
      },
      "id": "object_010",
      "properties": {
        "archetype": "atomic_composition",
        "bg_color": null,
        "bold": true,
        "color": [
          154,
          39,
          32
        ],
        "font_face": "Aptos",
        "font_size": 5,
        "italic": false,
        "kind": "caption",
        "margin": 0.03,
        "text": "Ladybug Theory Grumpy",
        "theme_topic": "Silent",
        "underline": false
      },
      "type": "text",
      "z_order": 10
    },
    {
      "bbox": {
        "h": 0.5885,
        "w": 2.3801,
        "x": 4.078,
        "y": 2.7684
      },
      "id": "object_011",
      "properties": {
        "archetype": "atomic_composition",
        "bg_color": [
          50,
          167,
          133
        ],
        "bold": false,
        "color": [
          29,
          101,
          95
        ],
        "font_face": "Aptos",
        "font_size": 13,
        "italic": true,
        "kind": "caption",
        "margin": 0.03,
        "text": "Ragged Skate",
        "theme_topic": "Silent",
        "underline": false
      },
      "type": "text",
      "z_order": 11
    },
    {
      "bbox": {
        "h": 0.538,
        "w": 0.846,
        "x": 7.2058,
        "y": 2.4234
      },
      "id": "object_012",
      "properties": {
        "archetype": "atomic_composition",
        "bg_color": null,
        "bold": false,
        "color": [
          113,
          128,
          98
        ],
        "font_face": "Aptos",
        "font_size": 9,
        "italic": false,
        "kind": "caption",
        "margin": 0.03,
        "text": "Wrist Delight Zippy",
        "theme_topic": "Silent",
        "underline": true
      },
      "type": "text",
      "z_order": 12
    },
    {
      "bbox": {
        "h": 0.5785,
        "w": 1.0819,
        "x": 4.0985,
        "y": 1.8655
      },
      "id": "object_013",
      "properties": {
        "archetype": "atomic_composition",
        "bg_color": [
          43,
          207,
          151
        ],
        "bold": false,
        "color": [
          136,
          188,
          103
        ],
        "font_face": "Aptos",
        "font_size": 14,
        "italic": false,
        "kind": "body",
        "margin": 0.04,
        "text": "test",
        "theme_topic": "Silent",
        "underline": true
      },
      "type": "text",
      "z_order": 13
    }
  ],
  "slide": {
    "height": 7.5,
    "image_file": "slide_000114.jpg",
    "width": 13.333
  },
  "version": 1
}