{
  "background": {
    "bbox": {
      "h": 7.5,
      "w": 13.333,
      "x": 0,
      "y": 0
    },
    "id": "object_000",
    "properties": {
      "archetype": "atomic_composition",
      "fill": [
        179,
        213,
        156
      ],
      "style": "solid",
      "theme_topic": "Grieving"
    },
    "type": "background",
    "z_order": 0
  },
  "objects": [
    {
      "bbox": {
        "h": 7.4982,
        "w": 0.6559,
        "x": 12.6603,
        "y": 0.0052
      },
      "id": "object_001",
      "properties": {
        "archetype": "atomic_composition",
        "dash": 1,
        "family": "panel",
        "fill": [
          156,
          186,
          136
        ],
        "line": [
          156,
          186,
          136
        ],
        "line_width": 4.4684480144133,
        "outline_only": false,
        "ppt_type": 1,
        "shape": "rect",
        "theme_topic": "Grieving"
      },
      "type": "shape",
      "z_order": 1
    },
    {
      "bbox": {
        "h": 1.0785,
        "w": 6.6222,
        "x": 0.57,
        "y": 0.3727
      },
      "id": "object_002",
      "properties": {
        "archetype": "atomic_composition",
        "bg_color": null,
        "bold": true,
        "color": [
          28,
          30,
          36
        ],
        "font_face": "Aptos Display",
        "font_size": 38,
        "italic": false,
        "kind": "header",
        "margin": 0.04,
        "text": "Writing Highfalutin",
        "theme_topic": "Grieving",
        "underline": false
      },
      "type": "text",
      "z_order": 2
    },
    {
      "bbox": {
        "h": 2.139,
        "w": 6.1787,
        "x": 6.6206,
        "y": 1.8673
      },
      "id": "object_003",
      "properties": {
        "archetype": "atomic_composition",
        "dash": 1,
        "family": "panel",
        "fill": [
          174,
          73,
          92
        ],
        "line": [
          156,
          186,
          136
        ],
        "line_width": 0.8378791268194663,
        "outline_only": false,
        "ppt_type": 5,
        "shape": "round_rect",
        "theme_topic": "Grieving"
      },
      "type": "shape",
      "z_order": 3
    },
    {
      "bbox": {
        "h": 0.8226,
        "w": 5.7852,
        "x": 6.7877,
        "y": 2.3039
      },
      "id": "object_004",
      "properties": {
        "archetype": "atomic_composition",
        "bg_color": null,
        "bold": true,
        "color": [
          179,
          213,
          156
        ],
        "font_face": "Aptos Display",
        "font_size": 44,
        "italic": false,
        "kind": "header",
        "margin": 0.04,
        "text": "72%",
        "theme_topic": "Grieving",
        "underline": false
      },
      "type": "text",
      "z_order": 4
    },
    {
      "bbox": {
        "h": 0.5119,
        "w": 5.7991,
        "x": 6.7953,
        "y": 3.1267
      },
      "id": "object_005",
      "properties": {
        "archetype": "atomic_composition",
        "bg_color": null,
        "bold": false,
        "color": [
          28,
          30,
          36
        ],
        "font_face": "Aptos",
        "font_size": 13,
        "italic": false,
        "kind": "body",
        "margin": 0.04,
        "text": "educate possess unique humdrum",
        "theme_topic": "Grieving",
        "underline": false
      },
      "type": "text",
      "z_order": 5
    },
    {
      "bbox": {
        "h": 5.1523,
        "w": 5.6267,
        "x": 0.5785,
        "y": 1.8583
      },
      "id": "object_006",
      "properties": {
        "archetype": "atomic_composition",
        "crop": [
          0.0034717429689036638,
          0.05316608683231677,
          0.025358554725037886,
          0.15945096196307912
        ],
        "focus": true,
        "mask_line": [
          194,
          161,
          186
        ],
        "mask_overlay": true,
        "theme_topic": "Grieving",
        "url": "https://picsum.photos/seed/aiimgslides/900/600"
      },
      "type": "image",
      "z_order": 6
    },
    {
      "bbox": {
        "h": 2.7623,
        "w": 1.2966,
        "x": 6.615,
        "y": 4.2545
      },
      "id": "object_007",
      "properties": {
        "archetype": "atomic_composition",
        "dash": 4,
        "family": "panel",
        "fill": [
          156,
          186,
          136
        ],
        "line": [
          156,
          186,
          136
        ],
        "line_width": 1.8377768366145333,
        "outline_only": false,
        "ppt_type": 5,
        "shape": "round_rect",
        "theme_topic": "Grieving"
      },
      "type": "shape",
      "z_order": 7
    },
    {
      "bbox": {
        "h": 0.5683,
        "w": 0.5829,
        "x": 6.801,
        "y": 4.4347
      },
      "id": "object_008",
      "properties": {
        "archetype": "atomic_composition",
        "dash": 5,
        "family": "stars",
        "fill": [
          33,
          103,
          218
        ],
        "focus": false,
        "line": [
          86,
          185,
          134
        ],
        "line_width": 5.8832272966964485,
        "outline_only": false,
        "ppt_type": 90,
        "shape": "explosion2",
        "theme_topic": "Grieving"
      },
      "type": "shape",
      "z_order": 8
    },
    {
      "bbox": {
        "h": 0.4539,
        "w": 0.7867,
        "x": 6.8421,
        "y": 5.1477
      },
      "id": "object_009",
      "properties": {
        "archetype": "atomic_composition",
        "bg_color": null,
        "bold": true,
        "color": [
          174,
          73,
          92
        ],
        "font_face": "Aptos",
        "font_size": 10,
        "italic": false,
        "kind": "caption",
        "margin": 0.03,
        "text": "Exercise",
        "theme_topic": "Grieving",
        "underline": false
      },
      "type": "text",
      "z_order": 9
    },
    {
      "bbox": {
        "h": 1.0847,
        "w": 0.8055,
        "x": 6.8737,
        "y": 5.6959
      },
      "id": "object_010",
      "properties": {
        "archetype": "atomic_composition",
        "bg_color": null,
        "bold": false,
        "color": [
          95,
          112,
          90
        ],
        "font_face": "Aptos",
        "font_size": 8,
        "italic": false,
        "kind": "body",
        "margin": 0.04,
        "text": "calculate act snotty scarecrow point pop foamy talk blush sigh empty",
        "theme_topic": "Grieving",
        "underline": false
      },
      "type": "text",
      "z_order": 10
    },
    {
      "bbox": {
        "h": 2.7422,
        "w": 1.3659,
        "x": 8.1253,
        "y": 4.2268
      },
      "id": "object_011",
      "properties": {
        "archetype": "atomic_composition",
        "dash": 1,
        "family": "panel",
        "fill": [
          156,
          186,
          136
        ],
        "line": [
          156,
          186,
          136
        ],
        "line_width": 5.098722415148766,
        "outline_only": false,
        "ppt_type": 5,
        "shape": "round_rect",
        "theme_topic": "Grieving"
      },
      "type": "shape",
      "z_order": 11
    },
    {
      "bbox": {
        "h": 0.5741,
        "w": 0.583,
        "x": 8.3045,
        "y": 4.4313
      },
      "id": "object_012",
      "properties": {
        "archetype": "atomic_composition",
        "dash": 1,
        "family": "flowchart",
        "fill": [
          156,
          186,
          136
        ],
        "focus": false,
        "line": [
          181,
          228,
          83
        ],
        "line_width": 6.088441069682189,
        "outline_only": true,
        "ppt_type": 61,
        "shape": "flow_process",
        "theme_topic": "Grieving"
      },
      "type": "shape",
      "z_order": 12
    },
    {
      "bbox": {
        "h": 0.4609,
        "w": 0.855,
        "x": 8.3906,
        "y": 5.1234
      },
      "id": "object_013",
      "properties": {
        "archetype": "atomic_composition",
        "bg_color": null,
        "bold": true,
        "color": [
          174,
          73,
          92
        ],
        "font_face": "Aptos",
        "font_size": 10,
        "italic": false,
        "kind": "caption",
        "margin": 0.03,
        "text": "Knee",
        "theme_topic": "Grieving",
        "underline": false
      },
      "type": "text",
      "z_order": 13
    },
    {
      "bbox": {
        "h": 1.103,
        "w": 0.8891,
        "x": 8.3494,
        "y": 5.6822
      },
      "id": "object_014",
      "properties": {
        "archetype": "atomic_composition",
        "bg_color": null,
        "bold": false,
        "color": [
          95,
          112,
          90
        ],
        "font_face": "Aptos",
        "font_size": 9,
        "italic": false,
        "kind": "body",
        "margin": 0.04,
        "text": "thrill card used note spot magnificent obnoxious scintillating stuff",
        "theme_topic": "Grieving",
        "underline": false
      },
      "type": "text",
      "z_order": 14
    },
    {
      "bbox": {
        "h": 2.7402,
        "w": 1.4566,
        "x": 9.7159,
        "y": 4.239
      },
      "id": "object_015",
      "properties": {
        "archetype": "atomic_composition",
        "dash": 1,
        "family": "panel",
        "fill": [
          156,
          186,
          136
        ],
        "line": [
          156,
          186,
          136
        ],
        "line_width": 4.007402567936661,
        "outline_only": false,
        "ppt_type": 5,
        "shape": "round_rect",
        "theme_topic": "Grieving"
      },
      "type": "shape",
      "z_order": 15
    },
    {
      "bbox": {
        "h": 0.5561,
        "w": 0.5859,
        "x": 9.9631,
        "y": 4.4596
      },
      "id": "object_016",
      "properties": {
        "archetype": "atomic_composition",
        "dash": 1,
        "family": "callouts",
        "fill": [
          203,
          139,
          192
        ],
        "focus": false,
        "line": [
          174,
          73,
          92
        ],
        "line_width": 2.344859883524705,
        "outline_only": true,
        "ppt_type": 106,
        "shape": "round_callout",
        "theme_topic": "Grieving"
      },
      "type": "shape",
      "z_order": 16
    },
    {
      "bbox": {
        "h": 0.4336,
        "w": 0.9547,
        "x": 9.9541,
        "y": 5.1256
      },
      "id": "object_017",
      "properties": {
        "archetype": "atomic_composition",
        "bg_color": null,
        "bold": true,
        "color": [
          174,
          73,
          92
        ],
        "font_face": "Aptos",
        "font_size": 11,
        "italic": false,
        "kind": "caption",
        "margin": 0.03,
        "text": "Omniscient",
        "theme_topic": "Grieving",
        "underline": false
      },
      "type": "text",
      "z_order": 17
    },
    {
      "bbox": {
        "h": 1.1263,
        "w": 0.9634,
        "x": 9.9699,
        "y": 5.6759
      },
      "id": "object_018",
      "properties": {
        "archetype": "atomic_composition",
        "bg_color": null,
        "bold": false,
        "color": [
          95,
          112,
          90
        ],
        "font_face": "Aptos",
        "font_size": 9,
        "italic": false,
        "kind": "body",
        "margin": 0.04,
        "text": "abortive watch cracker aunt slippery longing start porter sparkling door trouble want",
        "theme_topic": "Grieving",
        "underline": false
      },
      "type": "text",
      "z_order": 18
    },
    {
      "bbox": {
        "h": 2.7573,
        "w": 1.4031,
        "x": 11.3781,
        "y": 4.2452
      },
      "id": "object_019",
      "properties": {
        "archetype": "atomic_composition",
        "dash": 1,
        "family": "panel",
        "fill": [
          156,
          186,
          136
        ],
        "line": [
          156,
          186,
          136
        ],
        "line_width": 5.081231994520081,
        "outline_only": false,
        "ppt_type": 5,
        "shape": "round_rect",
        "theme_topic": "Grieving"
      },
      "type": "shape",
      "z_order": 19
    },
    {
      "bbox": {
        "h": 0.5563,
        "w": 0.579,
        "x": 11.6193,
        "y": 4.4493
      },
      "id": "object_020",
      "properties": {
        "archetype": "atomic_composition",
        "dash": 1,
        "family": "arrows",
        "fill": [
          41,
          218,
          198
        ],
        "focus": false,
        "line": [
          174,
          73,
          92
        ],
        "line_width": 3.1137302243478917,
        "outline_only": false,
        "ppt_type": 39,
        "shape": "quad_arrow",
        "theme_topic": "Grieving"
      },
      "type": "shape",
      "z_order": 20
    },
    {
      "bbox": {
        "h": 0.4711,
        "w": 0.9101,
        "x": 11.6423,
        "y": 5.1406
      },
      "id": "object_021",
      "properties": {
        "archetype": "atomic_composition",
        "bg_color": null,
        "bold": true,
        "color": [
          174,
          73,
          92
        ],
        "font_face": "Aptos",
        "font_size": 12,
        "italic": false,
        "kind": "caption",
        "margin": 0.03,
        "text": "Sassy Instrument",
        "theme_topic": "Grieving",
        "underline": false
      },
      "type": "text",
      "z_order": 21
    },
    {
      "bbox": {
        "h": 1.1152,
        "w": 0.8843,
        "x": 11.619,
        "y": 5.7025
      },
      "id": "object_022",
      "properties": {
        "archetype": "atomic_composition",
        "bg_color": null,
        "bold": false,
        "color": [
          95,
          112,
          90
        ],
        "font_face": "Aptos",
        "font_size": 8,
        "italic": false,
        "kind": "body",
        "margin": 0.04,
        "text": "symptomatic agreeable flaky frame far-flung chickens boast bikes cautious roof hook",
        "theme_topic": "Grieving",
        "underline": false
      },
      "type": "text",
      "z_order": 22
    },
    {
      "bbox": {
        "h": 0.4833,
        "w": 1.1544,
        "x": 5.4145,
        "y": 4.1101
      },
      "id": "object_023",
      "properties": {
        "archetype": "atomic_composition",
        "fill": [
          126,
          220,
          230
        ],
        "line": [
          65,
          228,
          63
        ],
        "line_width": 1.7380031884351603,
        "pattern": "badge",
        "points": [
          [
            0.5,
            0.0
          ],
          [
            0.62,
            0.25
          ],
          [
            0.92,
            0.18
          ],
          [
            0.75,
            0.5
          ],
          [
            0.98,
            0.78
          ],
          [
            0.62,
            0.72
          ],
          [
            0.5,
            1.0
          ],
          [
            0.38,
            0.72
          ],
          [
            0.02,
            0.78
          ],
          [
            0.25,
            0.5
          ],
          [
            0.08,
            0.18
          ],
          [
            0.38,
            0.25
          ]
        ],
        "theme_topic": "Grieving"
      },
      "type": "freeform",
      "z_order": 23
    },
    {
      "bbox": {
        "h": 0.4584,
        "w": 0.3969,
        "x": 12.5254,
        "y": 3.8049
      },
      "id": "object_024",
      "properties": {
        "archetype": "atomic_composition",
        "dash": 1,
        "family": "symbols",
        "fill": [
          160,
          144,
          182
        ],
        "focus": false,
        "line": [
          105,
          220,
          122
        ],
        "line_width": 3.086738746625276,
        "outline_only": false,
        "ppt_type": 13,
        "shape": "can",
        "theme_topic": "Grieving"
      },
      "type": "shape",
      "z_order": 24
    },
    {
      "bbox": {
        "h": 1.1511,
        "w": 0.5008,
        "x": 3.013,
        "y": 3.6847
      },
      "id": "object_025",
      "properties": {
        "archetype": "atomic_composition",
        "color": [
          152,
          90,
          112
        ],
        "connector": "straight",
        "dash": 1,
        "flip": false,
        "ppt_type": 1,
        "theme_topic": "Grieving",
        "width": 1.13549253667968
      },
      "type": "connector",
      "z_order": 25
    },
    {
      "bbox": {
        "h": 0.325,
        "w": 0.6527,
        "x": 0.1288,
        "y": 3.86
      },
      "id": "object_026",
      "properties": {
        "archetype": "atomic_composition",
        "dash": 7,
        "family": "basic",
        "fill": [
          225,
          53,
          223
        ],
        "focus": false,
        "line": [
          48,
          30,
          188
        ],
        "line_width": 2.6406620572718524,
        "outline_only": false,
        "ppt_type": 142,
        "shape": "pie",
        "theme_topic": "Grieving"
      },
      "type": "shape",
      "z_order": 26
    },
    {
      "bbox": {
        "h": 0.5841,
        "w": 0.8916,
        "x": 8.4307,
        "y": 4.6665
      },
      "id": "object_027",
      "properties": {
        "archetype": "atomic_composition",
        "bg_color": null,
        "bold": true,
        "color": [
          109,
          85,
          107
        ],
        "font_face": "Aptos",
        "font_size": 14,
        "italic": true,
        "kind": "caption",
        "margin": 0.03,
        "text": "Place Bikes",
        "theme_topic": "Grieving",
        "underline": false
      },
      "type": "text",
      "z_order": 27
    },
    {
      "bbox": {
        "h": 0.2,
        "w": 1.5442,
        "x": 4.0465,
        "y": 5.4374
      },
      "id": "object_028",
      "properties": {
        "archetype": "atomic_composition",
        "bg_color": null,
        "bold": false,
        "color": [
          33,
          216,
          118
        ],
        "font_face": "Aptos",
        "font_size": 8,
        "italic": false,
        "kind": "body",
        "margin": 0.04,
        "text": "remove birthday",
        "theme_topic": "Grieving",
        "underline": true
      },
      "type": "text",
      "z_order": 28
    },
    {
      "bbox": {
        "h": 0.6401,
        "w": 1.0434,
        "x": 0.7065,
        "y": 6.0112
      },
      "id": "object_029",
      "properties": {
        "archetype": "atomic_composition",
        "pattern": "swoop",
        "primary": [
          178,
          219,
          187
        ],
        "secondary": [
          64,
          130,
          109
        ],
        "svg": "<svg xmlns=\"http://www.w3.org/2000/svg\" width=\"400\" height=\"300\" viewBox=\"0 0 400 300\">\n        <path d=\"M22 196 C96 26 198 270 286 70 S372 92 386 204\"\n              fill=\"none\" stroke=\"#c0829a\" stroke-width=\"28\" stroke-linecap=\"round\"/>\n        <path d=\"M42 226 C124 112 214 288 360 126\"\n              fill=\"none\" stroke=\"#af69af\" stroke-width=\"12\" stroke-linecap=\"round\" opacity=\"0.85\"/>\n        </svg>",
        "theme_topic": "Grieving"
      },
      "type": "svg",
      "z_order": 29
    },
    {
      "bbox": {
        "h": 0.2798,
        "w": 1.0488,
        "x": 3.5257,
        "y": 4.1404
      },
      "id": "object_030",
      "properties": {
        "archetype": "atomic_composition",
        "dash": 1,
        "family": "flowchart",
        "fill": [
          205,
          132,
          129
        ],
        "focus": false,
        "line": [
          25,
          198,
          148
        ],
        "line_width": 5.102847528260253,
        "outline_only": false,
        "ppt_type": 65,
        "shape": "flow_predefined",
        "theme_topic": "Grieving"
      },
      "type": "shape",
      "z_order": 30
    },
    {
      "bbox": {
        "h": 0.3259,
        "w": 1.6349,
        "x": 4.7986,
        "y": 1.6919
      },
      "id": "object_031",
      "properties": {
        "archetype": "atomic_composition",
        "bg_color": null,
        "bold": true,
        "color": [
          69,
          222,
          73
        ],
        "font_face": "Aptos",
        "font_size": 8,
        "italic": false,
        "kind": "caption",
        "margin": 0.03,
        "text": "Sticks Satisfying Grotesque",
        "theme_topic": "Grieving",
        "underline": false
      },
      "type": "text",
      "z_order": 31
    }
  ],
  "slide": {
    "height": 7.5,
    "image_file": "slide_000635.jpg",
    "width": 13.333
  },
  "version": 1
}