{
  "background": {
    "bbox": {
      "h": 7.5,
      "w": 13.333,
      "x": 0,
      "y": 0
    },
    "id": "object_000",
    "properties": {
      "angle": 315,
      "archetype": "atomic_composition",
      "colors": [
        [
          97,
          99,
          121
        ],
        [
          71,
          221,
          181
        ]
      ],
      "fill": [
        61,
        64,
        91
      ],
      "focus": "center",
      "gradient_type": "shape",
      "style": "gradient",
      "theme_topic": "Full Secret"
    },
    "type": "background",
    "z_order": 0
  },
  "objects": [
    {
      "bbox": {
        "h": 1.6053,
        "w": 3.2848,
        "x": 6.8986,
        "y": 5.5924
      },
      "id": "object_001",
      "properties": {
        "archetype": "atomic_composition",
        "dash": 1,
        "family": "arrows",
        "fill": [
          163,
          63,
          142
        ],
        "focus": false,
        "line": [
          72,
          99,
          131
        ],
        "line_width": 4.562005082311224,
        "outline_only": true,
        "ppt_type": 53,
        "shape": "right_arrow_callout",
        "theme_topic": "Full Secret"
      },
      "type": "shape",
      "z_order": 1
    },
    {
      "bbox": {
        "h": 3.8175,
        "w": 7.6278,
        "x": 3.5788,
        "y": 3.2337
      },
      "id": "object_002",
      "properties": {
        "archetype": "atomic_composition",
        "dash": 1,
        "family": "symbols",
        "fill": [
          145,
          87,
          87
        ],
        "focus": false,
        "line": [
          97,
          72,
          60
        ],
        "line_width": 4.556449913156305,
        "outline_only": false,
        "ppt_type": 174,
        "shape": "funnel",
        "theme_topic": "Full Secret"
      },
      "type": "shape",
      "z_order": 2
    },
    {
      "bbox": {
        "h": 1.0251,
        "w": 13.3505,
        "x": 0.0033,
        "y": -0.0041
      },
      "id": "object_003",
      "properties": {
        "archetype": "atomic_composition",
        "dash": 4,
        "family": "panel",
        "fill": [
          97,
          99,
          121
        ],
        "line": [
          97,
          99,
          121
        ],
        "line_width": 3.395654299695382,
        "outline_only": false,
        "ppt_type": 1,
        "shape": "rect",
        "theme_topic": "Full Secret"
      },
      "type": "shape",
      "z_order": 3
    },
    {
      "bbox": {
        "h": 5.8201,
        "w": 3.2115,
        "x": 9.4121,
        "y": 0.6736
      },
      "id": "object_004",
      "properties": {
        "archetype": "atomic_composition",
        "bg_color": null,
        "bold": true,
        "color": [
          246,
          248,
          252
        ],
        "font_face": "Trebuchet MS",
        "font_size": 24,
        "italic": false,
        "kind": "header",
        "margin": 0.04,
        "text": "Tall Tall",
        "theme_topic": "Full Secret",
        "underline": false
      },
      "type": "text",
      "z_order": 4
    },
    {
      "bbox": {
        "h": 2.0004,
        "w": 2.6226,
        "x": 5.9819,
        "y": 4.2403
      },
      "id": "object_005",
      "properties": {
        "archetype": "atomic_composition",
        "dash": 5,
        "family": "panel",
        "fill": [
          97,
          99,
          121
        ],
        "line": [
          97,
          99,
          121
        ],
        "line_width": 2.23875063756347,
        "outline_only": false,
        "ppt_type": 5,
        "shape": "round_rect",
        "theme_topic": "Full Secret"
      },
      "type": "shape",
      "z_order": 5
    },
    {
      "bbox": {
        "h": 0.7152,
        "w": 2.3061,
        "x": 6.1874,
        "y": 4.6719
      },
      "id": "object_006",
      "properties": {
        "archetype": "atomic_composition",
        "bg_color": null,
        "bold": true,
        "color": [
          246,
          248,
          252
        ],
        "font_face": "Trebuchet MS",
        "font_size": 38,
        "italic": false,
        "kind": "header",
        "margin": 0.04,
        "text": "62%",
        "theme_topic": "Full Secret",
        "underline": false
      },
      "type": "text",
      "z_order": 6
    },
    {
      "bbox": {
        "h": 0.4482,
        "w": 2.2584,
        "x": 6.182,
        "y": 5.4234
      },
      "id": "object_007",
      "properties": {
        "archetype": "atomic_composition",
        "bg_color": null,
        "bold": false,
        "color": [
          246,
          248,
          252
        ],
        "font_face": "Verdana",
        "font_size": 11,
        "italic": false,
        "kind": "body",
        "margin": 0.04,
        "text": "sun bad capable well-groomed efficacious precede rifle hill neck",
        "theme_topic": "Full Secret",
        "underline": false
      },
      "type": "text",
      "z_order": 7
    },
    {
      "bbox": {
        "h": 3.9373,
        "w": 2.0785,
        "x": 0.7359,
        "y": 1.6335
      },
      "id": "object_008",
      "properties": {
        "archetype": "atomic_composition",
        "dash": 1,
        "family": "panel",
        "fill": [
          62,
          100,
          196
        ],
        "line": [
          97,
          99,
          121
        ],
        "line_width": 0.7656194842758821,
        "outline_only": false,
        "ppt_type": 5,
        "shape": "round_rect",
        "theme_topic": "Full Secret"
      },
      "type": "shape",
      "z_order": 8
    },
    {
      "bbox": {
        "h": 0.7452,
        "w": 1.7567,
        "x": 0.9259,
        "y": 1.7746
      },
      "id": "object_009",
      "properties": {
        "archetype": "atomic_composition",
        "bg_color": null,
        "bold": true,
        "color": [
          71,
          221,
          181
        ],
        "font_face": "Trebuchet MS",
        "font_size": 24,
        "italic": false,
        "kind": "header",
        "margin": 0.04,
        "text": "8.4x",
        "theme_topic": "Full Secret",
        "underline": false
      },
      "type": "text",
      "z_order": 9
    },
    {
      "bbox": {
        "h": 2.899,
        "w": 1.7267,
        "x": 0.9314,
        "y": 2.5598
      },
      "id": "object_010",
      "properties": {
        "archetype": "atomic_composition",
        "bg_color": null,
        "bold": false,
        "color": [
          162,
          165,
          179
        ],
        "font_face": "Verdana",
        "font_size": 13,
        "italic": false,
        "kind": "body",
        "margin": 0.04,
        "text": "fearless chickens tart border rate",
        "theme_topic": "Full Secret",
        "underline": false
      },
      "type": "text",
      "z_order": 10
    },
    {
      "bbox": {
        "h": 3.9275,
        "w": 2.3984,
        "x": 3.0006,
        "y": 1.6314
      },
      "id": "object_011",
      "properties": {
        "archetype": "atomic_composition",
        "dash": 5,
        "family": "panel",
        "fill": [
          46,
          93,
          33
        ],
        "line": [
          97,
          99,
          121
        ],
        "line_width": 2.753131712939933,
        "outline_only": false,
        "ppt_type": 5,
        "shape": "round_rect",
        "theme_topic": "Full Secret"
      },
      "type": "shape",
      "z_order": 11
    },
    {
      "bbox": {
        "h": 0.7502,
        "w": 2.0678,
        "x": 3.2018,
        "y": 1.8165
      },
      "id": "object_012",
      "properties": {
        "archetype": "atomic_composition",
        "bg_color": null,
        "bold": true,
        "color": [
          71,
          221,
          181
        ],
        "font_face": "Trebuchet MS",
        "font_size": 26,
        "italic": false,
        "kind": "header",
        "margin": 0.04,
        "text": "3.2x",
        "theme_topic": "Full Secret",
        "underline": false
      },
      "type": "text",
      "z_order": 12
    },
    {
      "bbox": {
        "h": 2.9063,
        "w": 2.0603,
        "x": 3.1853,
        "y": 2.5525
      },
      "id": "object_013",
      "properties": {
        "archetype": "atomic_composition",
        "bg_color": null,
        "bold": false,
        "color": [
          162,
          165,
          179
        ],
        "font_face": "Verdana",
        "font_size": 15,
        "italic": false,
        "kind": "body",
        "margin": 0.04,
        "text": "daily skate big bleach wry",
        "theme_topic": "Full Secret",
        "underline": false
      },
      "type": "text",
      "z_order": 13
    },
    {
      "bbox": {
        "h": 1.3116,
        "w": 1.7582,
        "x": 2.3722,
        "y": 1.8665
      },
      "id": "object_014",
      "properties": {
        "archetype": "atomic_composition",
        "dash": 3,
        "family": "panel",
        "fill": [
          97,
          99,
          121
        ],
        "line": [
          97,
          99,
          121
        ],
        "line_width": 3.550622061950647,
        "outline_only": false,
        "ppt_type": 5,
        "shape": "round_rect",
        "theme_topic": "Full Secret"
      },
      "type": "shape",
      "z_order": 14
    },
    {
      "bbox": {
        "h": 0.4179,
        "w": 1.3923,
        "x": 2.5404,
        "y": 2.2108
      },
      "id": "object_015",
      "properties": {
        "archetype": "atomic_composition",
        "bg_color": null,
        "bold": true,
        "color": [
          246,
          248,
          252
        ],
        "font_face": "Trebuchet MS",
        "font_size": 21,
        "italic": false,
        "kind": "header",
        "margin": 0.04,
        "text": "87%",
        "theme_topic": "Full Secret",
        "underline": false
      },
      "type": "text",
      "z_order": 15
    },
    {
      "bbox": {
        "h": 0.2852,
        "w": 1.3593,
        "x": 2.5596,
        "y": 2.6146
      },
      "id": "object_016",
      "properties": {
        "archetype": "atomic_composition",
        "bg_color": null,
        "bold": false,
        "color": [
          246,
          248,
          252
        ],
        "font_face": "Verdana",
        "font_size": 7,
        "italic": false,
        "kind": "body",
        "margin": 0.04,
        "text": "capricious merciful payment event lumber dysfunctional",
        "theme_topic": "Full Secret",
        "underline": false
      },
      "type": "text",
      "z_order": 16
    },
    {
      "bbox": {
        "h": 0.7944,
        "w": 0.2179,
        "x": 9.0363,
        "y": 4.4615
      },
      "id": "object_017",
      "properties": {
        "archetype": "atomic_composition",
        "dash": 1,
        "family": "arrows",
        "fill": [
          53,
          42,
          35
        ],
        "focus": false,
        "line": [
          133,
          71,
          97
        ],
        "line_width": 5.50724541924032,
        "outline_only": false,
        "ppt_type": 38,
        "shape": "up_down_arrow",
        "theme_topic": "Full Secret"
      },
      "type": "shape",
      "z_order": 17
    },
    {
      "bbox": {
        "h": 0.5359,
        "w": 2.2404,
        "x": 10.8039,
        "y": 2.7411
      },
      "id": "object_018",
      "properties": {
        "archetype": "atomic_composition",
        "bg_color": null,
        "bold": false,
        "color": [
          225,
          91,
          44
        ],
        "font_face": "Verdana",
        "font_size": 12,
        "italic": true,
        "kind": "caption",
        "margin": 0.03,
        "text": "Bright Request Roasted",
        "theme_topic": "Full Secret",
        "underline": false
      },
      "type": "text",
      "z_order": 18
    },
    {
      "bbox": {
        "h": 0.8403,
        "w": 1.3687,
        "x": 11.4658,
        "y": 2.9902
      },
      "id": "object_019",
      "properties": {
        "archetype": "atomic_composition",
        "dash": 2,
        "family": "arrows",
        "fill": [
          106,
          36,
          136
        ],
        "focus": false,
        "line": [
          80,
          119,
          133
        ],
        "line_width": 6.044309296698241,
        "outline_only": false,
        "ppt_type": 41,
        "shape": "bent_arrow",
        "theme_topic": "Full Secret"
      },
      "type": "shape",
      "z_order": 19
    },
    {
      "bbox": {
        "h": 0.7812,
        "w": 0.2,
        "x": 11.6801,
        "y": 4.5369
      },
      "id": "object_020",
      "properties": {
        "archetype": "atomic_composition",
        "dash": 1,
        "family": "symbols",
        "fill": [
          69,
          130,
          50
        ],
        "focus": false,
        "line": [
          192,
          176,
          97
        ],
        "line_width": 1.6737603619766974,
        "outline_only": false,
        "ppt_type": 22,
        "shape": "lightning",
        "theme_topic": "Full Secret"
      },
      "type": "shape",
      "z_order": 20
    },
    {
      "bbox": {
        "h": 0.4912,
        "w": 1.1532,
        "x": 3.4916,
        "y": 5.7996
      },
      "id": "object_021",
      "properties": {
        "archetype": "atomic_composition",
        "dash": 3,
        "family": "symbols",
        "fill": [
          208,
          166,
          200
        ],
        "focus": false,
        "line": [
          177,
          145,
          86
        ],
        "line_width": 1.091401543327133,
        "outline_only": true,
        "ppt_type": 22,
        "shape": "lightning",
        "theme_topic": "Full Secret"
      },
      "type": "shape",
      "z_order": 21
    },
    {
      "bbox": {
        "h": 0.9728,
        "w": 0.8147,
        "x": 3.1552,
        "y": 6.2229
      },
      "id": "object_022",
      "properties": {
        "archetype": "atomic_composition",
        "pattern": "swoop",
        "primary": [
          71,
          221,
          181
        ],
        "secondary": [
          228,
          49,
          163
        ],
        "svg": "<svg xmlns=\"http://www.w3.org/2000/svg\" width=\"400\" height=\"300\" viewBox=\"0 0 400 300\">\n        <path d=\"M22 196 C96 26 198 270 286 70 S372 92 386 204\"\n              fill=\"none\" stroke=\"#438c21\" stroke-width=\"28\" stroke-linecap=\"round\"/>\n        <path d=\"M42 226 C124 112 214 288 360 126\"\n              fill=\"none\" stroke=\"#c0bf5a\" stroke-width=\"12\" stroke-linecap=\"round\" opacity=\"0.85\"/>\n        </svg>",
        "theme_topic": "Full Secret"
      },
      "type": "svg",
      "z_order": 22
    }
  ],
  "slide": {
    "height": 7.5,
    "image_file": "slide_000258.jpg",
    "width": 13.333
  },
  "version": 1
}