{
  "background": {
    "bbox": {
      "h": 7.5,
      "w": 13.333,
      "x": 0,
      "y": 0
    },
    "id": "object_000",
    "properties": {
      "angle": 135,
      "archetype": "atomic_composition",
      "colors": [
        [
          189,
          133,
          36
        ],
        [
          122,
          70,
          214
        ]
      ],
      "fill": [
        232,
        163,
        45
      ],
      "focus": "bottom_right",
      "gradient_type": "rectangular",
      "style": "gradient",
      "theme_topic": "Riddle"
    },
    "type": "background",
    "z_order": 0
  },
  "curriculum": {
    "actual_content_count": 8,
    "level": 8,
    "max_level": 25,
    "slides_per_level": 40,
    "target_content_count": 8
  },
  "objects": [
    {
      "bbox": {
        "h": 4.7111,
        "w": 5.4606,
        "x": -0.7646,
        "y": 3.0735
      },
      "id": "object_001",
      "properties": {
        "archetype": "atomic_composition",
        "dash": 3,
        "family": "arrows",
        "fill": [
          212,
          168,
          114
        ],
        "focus": false,
        "line": [
          140,
          52,
          145
        ],
        "line_width": 2.2571029310246757,
        "outline_only": false,
        "ppt_type": 36,
        "shape": "down_arrow",
        "theme_topic": "Riddle"
      },
      "type": "shape",
      "z_order": 1
    },
    {
      "bbox": {
        "h": 4.3079,
        "w": 7.512,
        "x": 3.2366,
        "y": 0.7189
      },
      "id": "object_002",
      "properties": {
        "archetype": "atomic_composition",
        "dash": 1,
        "family": "symbols",
        "fill": [
          227,
          90,
          59
        ],
        "focus": false,
        "line": [
          116,
          148,
          130
        ],
        "line_width": 7.37487430587664,
        "outline_only": false,
        "ppt_type": 22,
        "shape": "lightning",
        "theme_topic": "Riddle"
      },
      "type": "shape",
      "z_order": 2
    },
    {
      "bbox": {
        "h": 1.1533,
        "w": 7.1702,
        "x": 2.7622,
        "y": 0.6429
      },
      "id": "object_003",
      "properties": {
        "archetype": "atomic_composition",
        "bg_color": null,
        "bold": true,
        "color": [
          28,
          30,
          36
        ],
        "font_face": "Arial",
        "font_size": 32,
        "italic": false,
        "kind": "header",
        "margin": 0.04,
        "text": "Abashed Doubtful Achiever Star",
        "theme_topic": "Riddle",
        "underline": false
      },
      "type": "text",
      "z_order": 3
    },
    {
      "bbox": {
        "h": 2.528,
        "w": 6.2065,
        "x": 0.5652,
        "y": 2.0172
      },
      "id": "object_004",
      "properties": {
        "archetype": "atomic_composition",
        "dash": 2,
        "family": "panel",
        "fill": [
          186,
          179,
          83
        ],
        "line": [
          189,
          133,
          36
        ],
        "line_width": 2.4291548580715316,
        "outline_only": false,
        "ppt_type": 5,
        "shape": "round_rect",
        "theme_topic": "Riddle"
      },
      "type": "shape",
      "z_order": 4
    },
    {
      "bbox": {
        "h": 1.4883,
        "w": 5.8606,
        "x": 0.7261,
        "y": 2.9116
      },
      "id": "object_005",
      "properties": {
        "archetype": "atomic_composition",
        "bg_color": null,
        "bold": false,
        "color": [
          119,
          89,
          40
        ],
        "font_face": "Arial",
        "font_size": 11,
        "italic": false,
        "kind": "body",
        "margin": 0.04,
        "text": "volatile likeable collect planes men",
        "theme_topic": "Riddle",
        "underline": false
      },
      "type": "text",
      "z_order": 5
    },
    {
      "bbox": {
        "h": 2.5262,
        "w": 5.8267,
        "x": 6.9299,
        "y": 2.0011
      },
      "id": "object_006",
      "properties": {
        "archetype": "atomic_composition",
        "dash": 1,
        "family": "panel",
        "fill": [
          186,
          179,
          83
        ],
        "line": [
          189,
          133,
          36
        ],
        "line_width": 1.1516030584329116,
        "outline_only": false,
        "ppt_type": 5,
        "shape": "round_rect",
        "theme_topic": "Riddle"
      },
      "type": "shape",
      "z_order": 6
    },
    {
      "bbox": {
        "h": 1.5117,
        "w": 5.49,
        "x": 7.122,
        "y": 2.9323
      },
      "id": "object_007",
      "properties": {
        "archetype": "atomic_composition",
        "bg_color": null,
        "bold": false,
        "color": [
          119,
          89,
          40
        ],
        "font_face": "Arial",
        "font_size": 12,
        "italic": false,
        "kind": "body",
        "margin": 0.04,
        "text": "volleyball mend spiffy late",
        "theme_topic": "Riddle",
        "underline": false
      },
      "type": "text",
      "z_order": 7
    },
    {
      "bbox": {
        "h": 2.1251,
        "w": 4.3659,
        "x": 4.818,
        "y": 4.93
      },
      "id": "object_008",
      "properties": {
        "archetype": "atomic_composition",
        "crop": [
          0.30644894282189616,
          0.07041962052517689,
          0.07086840039941095,
          0.06794779341256679
        ],
        "focus": true,
        "mask_line": [
          71,
          221,
          181
        ],
        "mask_overlay": false,
        "theme_topic": "Riddle",
        "url": "https://picsum.photos/seed/aiimgslides/900/600"
      },
      "type": "image",
      "z_order": 8
    }
  ],
  "slide": {
    "height": 7.5,
    "image_file": "slide_000285.jpg",
    "width": 13.333
  },
  "version": 1
}