{
  "background": {
    "bbox": {
      "h": 7.5,
      "w": 13.333,
      "x": 0,
      "y": 0
    },
    "id": "object_000",
    "properties": {
      "archetype": "atomic_composition",
      "fill": [
        28,
        143,
        112
      ],
      "style": "solid",
      "theme_topic": "Fit Worm"
    },
    "type": "background",
    "z_order": 0
  },
  "curriculum": {
    "actual_content_count": 13,
    "level": 13,
    "max_level": 25,
    "slides_per_level": 40,
    "target_content_count": 13
  },
  "objects": [
    {
      "bbox": {
        "h": 2.785,
        "w": 6.4788,
        "x": 0.0821,
        "y": 4.7934
      },
      "id": "object_001",
      "properties": {
        "archetype": "atomic_composition",
        "dash": 1,
        "family": "basic",
        "fill": [
          48,
          120,
          160
        ],
        "focus": false,
        "line": [
          77,
          162,
          100
        ],
        "line_width": 2.8855241056343597,
        "outline_only": true,
        "ppt_type": 142,
        "shape": "pie",
        "theme_topic": "Fit Worm"
      },
      "type": "shape",
      "z_order": 1
    },
    {
      "bbox": {
        "h": 4.9209,
        "w": 7.9519,
        "x": 0.9926,
        "y": -0.7218
      },
      "id": "object_002",
      "properties": {
        "archetype": "atomic_composition",
        "dash": 4,
        "family": "arrows",
        "fill": [
          118,
          184,
          54
        ],
        "focus": false,
        "line": [
          79,
          203,
          65
        ],
        "line_width": 7.33760690031408,
        "outline_only": false,
        "ppt_type": 34,
        "shape": "left_arrow",
        "theme_topic": "Fit Worm"
      },
      "type": "shape",
      "z_order": 2
    },
    {
      "bbox": {
        "h": 2.9631,
        "w": 6.9975,
        "x": 1.4055,
        "y": 4.77
      },
      "id": "object_003",
      "properties": {
        "archetype": "atomic_composition",
        "dash": 1,
        "family": "stars",
        "fill": [
          82,
          132,
          173
        ],
        "focus": false,
        "line": [
          63,
          64,
          52
        ],
        "line_width": 4.389292987787513,
        "outline_only": false,
        "ppt_type": 93,
        "shape": "star8",
        "theme_topic": "Fit Worm"
      },
      "type": "shape",
      "z_order": 3
    },
    {
      "bbox": {
        "h": 4.0054,
        "w": 7.3724,
        "x": 0.7923,
        "y": 0.6423
      },
      "id": "object_004",
      "properties": {
        "archetype": "atomic_composition",
        "dash": 1,
        "family": "panel",
        "fill": [
          37,
          155,
          123
        ],
        "line": [
          43,
          162,
          130
        ],
        "line_width": 0.8462076213817274,
        "outline_only": false,
        "ppt_type": 5,
        "shape": "round_rect",
        "theme_topic": "Fit Worm"
      },
      "type": "shape",
      "z_order": 4
    },
    {
      "bbox": {
        "h": 1.1932,
        "w": 7.3692,
        "x": 0.5415,
        "y": 0.3251
      },
      "id": "object_005",
      "properties": {
        "archetype": "atomic_composition",
        "bg_color": null,
        "bold": true,
        "color": [
          248,
          255,
          252
        ],
        "font_face": "Trebuchet MS",
        "font_size": 33,
        "italic": false,
        "kind": "header",
        "margin": 0.04,
        "text": "Boat Adamant Wash Chunky",
        "theme_topic": "Fit Worm",
        "underline": false
      },
      "type": "text",
      "z_order": 5
    },
    {
      "bbox": {
        "h": 0.8887,
        "w": 5.9883,
        "x": 6.6774,
        "y": 1.9465
      },
      "id": "object_006",
      "properties": {
        "archetype": "atomic_composition",
        "bg_color": null,
        "bold": true,
        "color": [
          110,
          204,
          186
        ],
        "font_face": "Trebuchet MS",
        "font_size": 36,
        "italic": false,
        "kind": "header",
        "margin": 0.04,
        "text": "Futuristic Immense",
        "theme_topic": "Fit Worm",
        "underline": false
      },
      "type": "text",
      "z_order": 6
    },
    {
      "bbox": {
        "h": 1.1973,
        "w": 5.9788,
        "x": 6.6327,
        "y": 3.0947
      },
      "id": "object_007",
      "properties": {
        "archetype": "atomic_composition",
        "bg_color": null,
        "bold": false,
        "color": [
          205,
          241,
          230
        ],
        "font_face": "Verdana",
        "font_size": 10,
        "italic": false,
        "kind": "body",
        "margin": 0.04,
        "text": "mice purpose picayune incredible lively effect house earthy callous receptive imaginary overt makeshift amazing bloody extra-large sleet careful",
        "theme_topic": "Fit Worm",
        "underline": false
      },
      "type": "text",
      "z_order": 7
    },
    {
      "bbox": {
        "h": 2.5851,
        "w": 5.6967,
        "x": 0.581,
        "y": 1.84
      },
      "id": "object_008",
      "properties": {
        "archetype": "atomic_composition",
        "crop": [
          0.2803280778421283,
          0.0033922241412182685,
          0.18782436411018164,
          0.1890799415684452
        ],
        "focus": true,
        "mask_line": [
          255,
          238,
          103
        ],
        "mask_overlay": false,
        "theme_topic": "Fit Worm",
        "url": "https://picsum.photos/seed/aiimgslides/900/600"
      },
      "type": "image",
      "z_order": 8
    },
    {
      "bbox": {
        "h": 0.2619,
        "w": 5.2681,
        "x": 0.76,
        "y": 3.9902
      },
      "id": "object_009",
      "properties": {
        "archetype": "atomic_composition",
        "bg_color": null,
        "bold": true,
        "color": [
          255,
          238,
          103
        ],
        "font_face": "Verdana",
        "font_size": 10,
        "italic": false,
        "kind": "caption",
        "margin": 0.03,
        "text": "Lighten Tire Empty",
        "theme_topic": "Fit Worm",
        "underline": false
      },
      "type": "text",
      "z_order": 9
    },
    {
      "bbox": {
        "h": 2.1592,
        "w": 12.1193,
        "x": 0.6045,
        "y": 4.8037
      },
      "id": "object_010",
      "properties": {
        "archetype": "atomic_composition",
        "band": [
          212,
          41,
          114
        ],
        "band_cols": false,
        "band_rows": false,
        "body": [
          43,
          162,
          130
        ],
        "border": [
          205,
          241,
          230
        ],
        "border_dash": "solid",
        "border_width": 2.256016026081515,
        "cells": [
          [
            "channel confused",
            "damaged",
            "piquant"
          ],
          [
            "awful",
            "dolls placid",
            "instrument bizarre"
          ],
          [
            "star",
            "entertain",
            "tramp defeated"
          ],
          [
            "day",
            "brash",
            "calculate lie"
          ],
          [
            "nondescript",
            "shame",
            "haircut plough"
          ],
          [
            "economic",
            "unit",
            "approve"
          ],
          [
            "wakeful",
            "bucket",
            "spiky coat"
          ]
        ],
        "cols": 3,
        "font_size": 7,
        "has_header": true,
        "header": [
          212,
          227,
          86
        ],
        "rows": 7,
        "text_color": [
          248,
          255,
          252
        ],
        "theme_topic": "Fit Worm"
      },
      "type": "table",
      "z_order": 10
    },
    {
      "bbox": {
        "h": 0.6838,
        "w": 1.6968,
        "x": 8.9431,
        "y": 2.7048
      },
      "id": "object_011",
      "properties": {
        "archetype": "atomic_composition",
        "color": [
          180,
          184,
          55
        ],
        "connector": "elbow",
        "dash": 3,
        "flip": true,
        "ppt_type": 2,
        "theme_topic": "Fit Worm",
        "width": 0.35323951057368835
      },
      "type": "connector",
      "z_order": 11
    },
    {
      "bbox": {
        "h": 0.7962,
        "w": 1.2349,
        "x": 2.0123,
        "y": 0.2252
      },
      "id": "object_012",
      "properties": {
        "archetype": "atomic_composition",
        "dash": 1,
        "family": "basic",
        "fill": [
          230,
          187,
          102
        ],
        "focus": false,
        "line": [
          137,
          143,
          38
        ],
        "line_width": 6.009671358017574,
        "outline_only": true,
        "ppt_type": 103,
        "shape": "wave",
        "theme_topic": "Fit Worm"
      },
      "type": "shape",
      "z_order": 12
    },
    {
      "bbox": {
        "h": 0.951,
        "w": 0.2,
        "x": 0.2568,
        "y": 4.4163
      },
      "id": "object_013",
      "properties": {
        "archetype": "atomic_composition",
        "dash": 3,
        "family": "basic",
        "fill": [
          115,
          178,
          45
        ],
        "focus": false,
        "line": [
          133,
          31,
          214
        ],
        "line_width": 1.1012237755095067,
        "outline_only": false,
        "ppt_type": 2,
        "shape": "parallelogram",
        "theme_topic": "Fit Worm"
      },
      "type": "shape",
      "z_order": 13
    }
  ],
  "slide": {
    "height": 7.5,
    "image_file": "slide_000520.jpg",
    "width": 13.333
  },
  "version": 1
}