{
  "background": {
    "bbox": {
      "h": 7.5,
      "w": 13.333,
      "x": 0,
      "y": 0
    },
    "id": "object_000",
    "properties": {
      "archetype": "atomic_composition",
      "back_color": [
        242,
        233,
        222
      ],
      "fill": [
        252,
        249,
        244
      ],
      "fore_color": [
        174,
        73,
        92
      ],
      "pattern": 44,
      "style": "pattern",
      "theme_topic": "Ink Drop"
    },
    "type": "background",
    "z_order": 0
  },
  "curriculum": {
    "actual_content_count": 10,
    "level": 10,
    "max_level": 25,
    "slides_per_level": 40,
    "target_content_count": 10
  },
  "objects": [
    {
      "bbox": {
        "h": 1.8755,
        "w": 8.1579,
        "x": 2.6379,
        "y": 1.3871
      },
      "id": "object_001",
      "properties": {
        "archetype": "atomic_composition",
        "dash": 1,
        "family": "callouts",
        "fill": [
          102,
          157,
          183
        ],
        "focus": false,
        "line": [
          179,
          186,
          77
        ],
        "line_width": 5.181516393935164,
        "outline_only": false,
        "ppt_type": 106,
        "shape": "round_callout",
        "theme_topic": "Ink Drop"
      },
      "type": "shape",
      "z_order": 1
    },
    {
      "bbox": {
        "h": 5.8088,
        "w": 3.1968,
        "x": 9.3793,
        "y": 0.6279
      },
      "id": "object_002",
      "properties": {
        "archetype": "atomic_composition",
        "bg_color": null,
        "bold": true,
        "color": [
          36,
          32,
          29
        ],
        "font_face": "Aptos Display",
        "font_size": 21,
        "italic": false,
        "kind": "header",
        "margin": 0.04,
        "text": "Glow Feeble",
        "theme_topic": "Ink Drop",
        "underline": false
      },
      "type": "text",
      "z_order": 2
    },
    {
      "bbox": {
        "h": 3.6332,
        "w": 3.4966,
        "x": 5.1692,
        "y": 0.8749
      },
      "id": "object_003",
      "properties": {
        "archetype": "atomic_composition",
        "bg_color": null,
        "bold": true,
        "color": [
          36,
          32,
          29
        ],
        "font_face": "Aptos Display",
        "font_size": 29,
        "italic": false,
        "kind": "header",
        "margin": 0.04,
        "text": "Dad Courageous Whole Protect Violet Pedal Hole Moan Burly",
        "theme_topic": "Ink Drop",
        "underline": false
      },
      "type": "text",
      "z_order": 3
    },
    {
      "bbox": {
        "h": 1.0557,
        "w": 1.8976,
        "x": 5.1852,
        "y": 5.0647
      },
      "id": "object_004",
      "properties": {
        "archetype": "atomic_composition",
        "bg_color": null,
        "bold": true,
        "color": [
          174,
          73,
          92
        ],
        "font_face": "Aptos",
        "font_size": 9,
        "italic": false,
        "kind": "caption",
        "margin": 0.03,
        "text": "QUESTIONABLE",
        "theme_topic": "Ink Drop",
        "underline": false
      },
      "type": "text",
      "z_order": 4
    },
    {
      "bbox": {
        "h": 0.2874,
        "w": 3.7053,
        "x": 0.7834,
        "y": 0.7906
      },
      "id": "object_005",
      "properties": {
        "archetype": "atomic_composition",
        "bg_color": null,
        "bold": true,
        "color": [
          174,
          73,
          92
        ],
        "font_face": "Aptos",
        "font_size": 12,
        "italic": false,
        "kind": "caption",
        "margin": 0.03,
        "text": "ROB",
        "theme_topic": "Ink Drop",
        "underline": false
      },
      "type": "text",
      "z_order": 5
    },
    {
      "bbox": {
        "h": 1.0663,
        "w": 3.7191,
        "x": 0.8049,
        "y": 1.2279
      },
      "id": "object_006",
      "properties": {
        "archetype": "atomic_composition",
        "bg_color": null,
        "bold": true,
        "color": [
          132,
          219,
          221
        ],
        "font_face": "Aptos Display",
        "font_size": 29,
        "italic": true,
        "kind": "header",
        "margin": 0.04,
        "text": "Note Smoke Bawdy Enter",
        "theme_topic": "Ink Drop",
        "underline": false
      },
      "type": "text",
      "z_order": 6
    },
    {
      "bbox": {
        "h": 4.211,
        "w": 3.7045,
        "x": 0.7979,
        "y": 2.5635
      },
      "id": "object_007",
      "properties": {
        "archetype": "atomic_composition",
        "bg_color": null,
        "bold": false,
        "color": [
          123,
          113,
          103
        ],
        "font_face": "Aptos",
        "font_size": 14,
        "italic": false,
        "kind": "body",
        "margin": 0.04,
        "text": "enchanted bloody volatile better chief loud devilish true cheer hysterical identify ill peck talented",
        "theme_topic": "Ink Drop",
        "underline": false
      },
      "type": "text",
      "z_order": 7
    },
    {
      "bbox": {
        "h": 0.4241,
        "w": 1.5686,
        "x": 5.8827,
        "y": 0.7593
      },
      "id": "object_008",
      "properties": {
        "archetype": "atomic_composition",
        "bg_color": [
          218,
          33,
          155
        ],
        "bold": false,
        "color": [
          51,
          103,
          140
        ],
        "font_face": "Aptos",
        "font_size": 11,
        "italic": false,
        "kind": "body",
        "margin": 0.04,
        "text": "grey nasty explain pour",
        "theme_topic": "Ink Drop",
        "underline": false
      },
      "type": "text",
      "z_order": 8
    },
    {
      "bbox": {
        "h": 0.2901,
        "w": 0.9792,
        "x": 0.9099,
        "y": 0.9162
      },
      "id": "object_009",
      "properties": {
        "archetype": "atomic_composition",
        "dash": 3,
        "family": "basic",
        "fill": [
          33,
          229,
          70
        ],
        "focus": false,
        "line": [
          27,
          46,
          131
        ],
        "line_width": 5.459441721403236,
        "outline_only": true,
        "ppt_type": 142,
        "shape": "pie",
        "theme_topic": "Ink Drop"
      },
      "type": "shape",
      "z_order": 9
    },
    {
      "bbox": {
        "h": 0.4137,
        "w": 1.1395,
        "x": 4.4532,
        "y": 5.2531
      },
      "id": "object_010",
      "properties": {
        "archetype": "atomic_composition",
        "bg_color": null,
        "bold": false,
        "color": [
          166,
          168,
          174
        ],
        "font_face": "Aptos",
        "font_size": 17,
        "italic": true,
        "kind": "body",
        "margin": 0.04,
        "text": "worm acid",
        "theme_topic": "Ink Drop",
        "underline": false
      },
      "type": "text",
      "z_order": 10
    }
  ],
  "slide": {
    "height": 7.5,
    "image_file": "slide_000376.jpg",
    "width": 13.333
  },
  "version": 1
}