{
  "background": {
    "bbox": {
      "h": 7.5,
      "w": 13.333,
      "x": 0,
      "y": 0
    },
    "id": "object_000",
    "properties": {
      "angle": 225,
      "archetype": "atomic_composition",
      "colors": [
        [
          49,
          145,
          162
        ],
        [
          168,
          54,
          94
        ]
      ],
      "fill": [
        18,
        129,
        148
      ],
      "focus": "bottom_right",
      "gradient_type": "linear",
      "style": "gradient",
      "theme_topic": "Parcel"
    },
    "type": "background",
    "z_order": 0
  },
  "objects": [
    {
      "bbox": {
        "h": 0.7199,
        "w": 13.3443,
        "x": -0.0112,
        "y": 0.0074
      },
      "id": "object_001",
      "properties": {
        "archetype": "atomic_composition",
        "dash": 2,
        "family": "panel",
        "fill": [
          49,
          145,
          162
        ],
        "line": [
          49,
          145,
          162
        ],
        "line_width": 5.214816647361985,
        "outline_only": false,
        "ppt_type": 1,
        "shape": "rect",
        "theme_topic": "Parcel"
      },
      "type": "shape",
      "z_order": 1
    },
    {
      "bbox": {
        "h": 3.1752,
        "w": 1.3689,
        "x": 8.5216,
        "y": 0.5628
      },
      "id": "object_002",
      "properties": {
        "archetype": "atomic_composition",
        "dash": 7,
        "family": "panel",
        "fill": [
          40,
          151,
          146
        ],
        "line": [
          49,
          145,
          162
        ],
        "line_width": 1.4491931137759526,
        "outline_only": false,
        "ppt_type": 5,
        "shape": "round_rect",
        "theme_topic": "Parcel"
      },
      "type": "shape",
      "z_order": 2
    },
    {
      "bbox": {
        "h": 0.7313,
        "w": 0.9998,
        "x": 8.6711,
        "y": 0.7439
      },
      "id": "object_003",
      "properties": {
        "archetype": "atomic_composition",
        "bg_color": null,
        "bold": true,
        "color": [
          32,
          119,
          149
        ],
        "font_face": "Arial",
        "font_size": 26,
        "italic": false,
        "kind": "header",
        "margin": 0.04,
        "text": "5.3x",
        "theme_topic": "Parcel",
        "underline": false
      },
      "type": "text",
      "z_order": 3
    },
    {
      "bbox": {
        "h": 2.1441,
        "w": 0.9937,
        "x": 8.6678,
        "y": 1.4766
      },
      "id": "object_004",
      "properties": {
        "archetype": "atomic_composition",
        "bg_color": null,
        "bold": false,
        "color": [
          143,
          194,
          205
        ],
        "font_face": "Arial",
        "font_size": 13,
        "italic": false,
        "kind": "body",
        "margin": 0.04,
        "text": "bow illustrious announce",
        "theme_topic": "Parcel",
        "underline": false
      },
      "type": "text",
      "z_order": 4
    },
    {
      "bbox": {
        "h": 3.1906,
        "w": 1.1858,
        "x": 10.043,
        "y": 0.5393
      },
      "id": "object_005",
      "properties": {
        "archetype": "atomic_composition",
        "dash": 1,
        "family": "panel",
        "fill": [
          67,
          146,
          114
        ],
        "line": [
          49,
          145,
          162
        ],
        "line_width": 1.432275634085847,
        "outline_only": false,
        "ppt_type": 5,
        "shape": "round_rect",
        "theme_topic": "Parcel"
      },
      "type": "shape",
      "z_order": 5
    },
    {
      "bbox": {
        "h": 0.7428,
        "w": 0.8402,
        "x": 10.2256,
        "y": 0.746
      },
      "id": "object_006",
      "properties": {
        "archetype": "atomic_composition",
        "bg_color": null,
        "bold": true,
        "color": [
          32,
          119,
          149
        ],
        "font_face": "Arial",
        "font_size": 28,
        "italic": false,
        "kind": "header",
        "margin": 0.04,
        "text": "3.9x",
        "theme_topic": "Parcel",
        "underline": false
      },
      "type": "text",
      "z_order": 6
    },
    {
      "bbox": {
        "h": 2.1629,
        "w": 0.8182,
        "x": 10.226,
        "y": 1.4842
      },
      "id": "object_007",
      "properties": {
        "archetype": "atomic_composition",
        "bg_color": null,
        "bold": false,
        "color": [
          143,
          194,
          205
        ],
        "font_face": "Arial",
        "font_size": 11,
        "italic": false,
        "kind": "body",
        "margin": 0.04,
        "text": "flame salty head resolute quickest",
        "theme_topic": "Parcel",
        "underline": false
      },
      "type": "text",
      "z_order": 7
    },
    {
      "bbox": {
        "h": 3.1801,
        "w": 1.3685,
        "x": 11.3927,
        "y": 0.5386
      },
      "id": "object_008",
      "properties": {
        "archetype": "atomic_composition",
        "dash": 1,
        "family": "panel",
        "fill": [
          49,
          145,
          162
        ],
        "line": [
          49,
          145,
          162
        ],
        "line_width": 2.328844060663761,
        "outline_only": false,
        "ppt_type": 5,
        "shape": "round_rect",
        "theme_topic": "Parcel"
      },
      "type": "shape",
      "z_order": 8
    },
    {
      "bbox": {
        "h": 0.7679,
        "w": 1.0229,
        "x": 11.5761,
        "y": 0.7509
      },
      "id": "object_009",
      "properties": {
        "archetype": "atomic_composition",
        "bg_color": null,
        "bold": true,
        "color": [
          32,
          119,
          149
        ],
        "font_face": "Arial",
        "font_size": 27,
        "italic": false,
        "kind": "header",
        "margin": 0.04,
        "text": "4.4x",
        "theme_topic": "Parcel",
        "underline": false
      },
      "type": "text",
      "z_order": 9
    },
    {
      "bbox": {
        "h": 2.1573,
        "w": 1.0126,
        "x": 11.5994,
        "y": 1.4745
      },
      "id": "object_010",
      "properties": {
        "archetype": "atomic_composition",
        "bg_color": null,
        "bold": false,
        "color": [
          143,
          194,
          205
        ],
        "font_face": "Arial",
        "font_size": 11,
        "italic": false,
        "kind": "body",
        "margin": 0.04,
        "text": "cheerful colorful innate impress volleyball snatch",
        "theme_topic": "Parcel",
        "underline": false
      },
      "type": "text",
      "z_order": 10
    },
    {
      "bbox": {
        "h": 0.3008,
        "w": 3.9696,
        "x": 4.0647,
        "y": 0.647
      },
      "id": "object_011",
      "properties": {
        "archetype": "atomic_composition",
        "bg_color": null,
        "bold": true,
        "color": [
          32,
          119,
          149
        ],
        "font_face": "Arial",
        "font_size": 9,
        "italic": false,
        "kind": "caption",
        "margin": 0.03,
        "text": "DIVISION CUTE",
        "theme_topic": "Parcel",
        "underline": false
      },
      "type": "text",
      "z_order": 11
    },
    {
      "bbox": {
        "h": 0.9294,
        "w": 3.9686,
        "x": 4.0533,
        "y": 1.1306
      },
      "id": "object_012",
      "properties": {
        "archetype": "atomic_composition",
        "bg_color": null,
        "bold": true,
        "color": [
          143,
          54,
          140
        ],
        "font_face": "Arial",
        "font_size": 44,
        "italic": false,
        "kind": "header",
        "margin": 0.04,
        "text": "Nimble",
        "theme_topic": "Parcel",
        "underline": false
      },
      "type": "text",
      "z_order": 12
    },
    {
      "bbox": {
        "h": 1.2539,
        "w": 3.9714,
        "x": 4.0434,
        "y": 2.3525
      },
      "id": "object_013",
      "properties": {
        "archetype": "atomic_composition",
        "bg_color": null,
        "bold": false,
        "color": [
          143,
          194,
          205
        ],
        "font_face": "Arial",
        "font_size": 11,
        "italic": false,
        "kind": "body",
        "margin": 0.04,
        "text": "enchanting fail scintillating children cow remain pop melodic death agreeable sudden disillusioned waste laughable intelligent crazy cheap tub",
        "theme_topic": "Parcel",
        "underline": false
      },
      "type": "text",
      "z_order": 13
    },
    {
      "bbox": {
        "h": 0.6714,
        "w": 0.9771,
        "x": 5.7636,
        "y": 2.4131
      },
      "id": "object_014",
      "properties": {
        "archetype": "atomic_composition",
        "pattern": "burst",
        "primary": [
          32,
          119,
          149
        ],
        "secondary": [
          86,
          65,
          84
        ],
        "svg": "<svg xmlns=\"http://www.w3.org/2000/svg\" width=\"400\" height=\"300\" viewBox=\"0 0 400 300\">\n        <path d=\"M200 10 L226 86 L306 52 L268 126 L386 132 L278 168 L332 240 L236 194 L200 290 L166 196 L70 240 L124 168 L14 132 L132 126 L94 52 L174 86 Z\"\n              fill=\"#46424a\" opacity=\"0.78\"/>\n        <path d=\"M200 82 L226 145 L294 146 L238 184 L258 252 L200 212 L142 252 L162 184 L106 146 L174 145 Z\"\n              fill=\"#3f745b\" opacity=\"0.72\"/>\n        </svg>",
        "theme_topic": "Parcel"
      },
      "type": "svg",
      "z_order": 14
    },
    {
      "bbox": {
        "h": 0.162,
        "w": 1.1042,
        "x": 11.3976,
        "y": 4.2892
      },
      "id": "object_015",
      "properties": {
        "archetype": "atomic_composition",
        "color": [
          228,
          142,
          71
        ],
        "connector": "curve",
        "dash": 3,
        "flip": true,
        "ppt_type": 3,
        "theme_topic": "Parcel",
        "width": 0.33984149657809665
      },
      "type": "connector",
      "z_order": 15
    },
    {
      "bbox": {
        "h": 0.4627,
        "w": 1.2263,
        "x": 4.3128,
        "y": 2.3715
      },
      "id": "object_016",
      "properties": {
        "archetype": "atomic_composition",
        "bg_color": null,
        "bold": true,
        "color": [
          95,
          145,
          82
        ],
        "font_face": "Arial",
        "font_size": 6,
        "italic": false,
        "kind": "caption",
        "margin": 0.03,
        "text": "Vigorous",
        "theme_topic": "Parcel",
        "underline": true
      },
      "type": "text",
      "z_order": 16
    },
    {
      "bbox": {
        "h": 0.2159,
        "w": 0.2858,
        "x": 5.5725,
        "y": 6.1701
      },
      "id": "object_017",
      "properties": {
        "archetype": "atomic_composition",
        "dash": 1,
        "family": "ribbons",
        "fill": [
          75,
          220,
          189
        ],
        "focus": false,
        "line": [
          68,
          217,
          60
        ],
        "line_width": 3.236544813536201,
        "outline_only": false,
        "ppt_type": 97,
        "shape": "up_ribbon",
        "theme_topic": "Parcel"
      },
      "type": "shape",
      "z_order": 17
    },
    {
      "bbox": {
        "h": 0.4053,
        "w": 0.8785,
        "x": 5.3549,
        "y": 2.6226
      },
      "id": "object_018",
      "properties": {
        "archetype": "atomic_composition",
        "dash": 1,
        "family": "symbols",
        "fill": [
          193,
          146,
          62
        ],
        "focus": false,
        "line": [
          102,
          191,
          199
        ],
        "line_width": 3.703684324234082,
        "outline_only": false,
        "ppt_type": 24,
        "shape": "moon",
        "theme_topic": "Parcel"
      },
      "type": "shape",
      "z_order": 18
    },
    {
      "bbox": {
        "h": 0.5911,
        "w": 0.7762,
        "x": 0.6095,
        "y": 2.8883
      },
      "id": "object_019",
      "properties": {
        "archetype": "atomic_composition",
        "bg_color": null,
        "bold": false,
        "color": [
          139,
          123,
          66
        ],
        "font_face": "Arial",
        "font_size": 7,
        "italic": false,
        "kind": "caption",
        "margin": 0.03,
        "text": "Curious Plucky Year",
        "theme_topic": "Parcel",
        "underline": false
      },
      "type": "text",
      "z_order": 19
    },
    {
      "bbox": {
        "h": 0.5847,
        "w": 0.84,
        "x": 2.6724,
        "y": 4.2487
      },
      "id": "object_020",
      "properties": {
        "archetype": "atomic_composition",
        "bg_color": [
          109,
          26,
          224
        ],
        "bold": true,
        "color": [
          107,
          39,
          111
        ],
        "font_face": "Arial",
        "font_size": 11,
        "italic": true,
        "kind": "caption",
        "margin": 0.03,
        "text": "Property Psychotic Unequaled",
        "theme_topic": "Parcel",
        "underline": false
      },
      "type": "text",
      "z_order": 20
    }
  ],
  "slide": {
    "height": 7.5,
    "image_file": "slide_000697.jpg",
    "width": 13.333
  },
  "version": 1
}